{
	// Place your snippets for html here. Each snippet is defined under a snippet name and has a prefix, body and 
	// description. The prefix is what is used to trigger the snippet and the body will be expanded and inserted. Possible variables are:
	// $1, $2 for tab stops, $0 for the final cursor position, and ${1:label}, ${2:another} for placeholders. Placeholders with the 
	// same ids are connected.
	// Example:
	"Get html with jquery": {
		"prefix": "sshtml",
		"body": [
				"<!DOCTYPE html>",
				"<html lang=\"en\">",
				"<head>",
					"<meta charset=\"UTF-8\">",
					"<meta name=\"viewport\" content=\"width=device-width, initial-scale=1.0\">",
					"<title>Document</title>",
					"<script src=\"https://ajax.googleapis.com/ajax/libs/jquery/3.5.1/jquery.min.js\"></script>",
					"<script>",
					"$(document).ready(function(){",
					"console.log('hello world mad');", 
					"});",
					"</script>",
				"</head>",
				"<body>", 
				"$1",
				"</body>",
				"</html>",
		],
		"description": "Get html with jquery"
	},
	"Commnet": {
		"prefix": ["comment", "cc"],
		"body": [
				"<!-- $1 -->",
		],
		"description": "Comment"
	},
	"angular html error": {
		"prefix": ["sserror"],
		"body": [
			"<div *ngIf='${1:f}.${2:fname}.touched && ${1:f}.${2:fname}.invalid' class='alert alert-danger'>",
			"\t<div *ngIf='${1:f}.${2:fname}.errors.required'>${3:First name} is required.</div>",
			"\t<div *ngIf='${1:f}.${2:fname}.errors.minlength'>${3:First name} should be 3 character.</div>",
			"\t<div *ngIf='${1:f}.${2:fname}.errors.maxlength'>${3:First name} should be 10 character.</div>",
			"</div>" ,
		],
		"description": "Comment"
	},
	"Div with comment": {
		"prefix": "ssdiv",
		"body": ["<div class='$1'>$2</div><!-- $1 -->"],
		"description": "Div with comment"
	
	},
	"NBSP": {
		"prefix": "ssnbsp",
		"body": ["&nbsp;"],
		"description": "NBSP"
	}
}